{
 "aggregate_function_based_on": "",
 "creation": "2021-11-10 17:08:20.693196",
 "docstatus": 0,
 "doctype": "Number Card",
 "document_type": "GL Entry",
 "dynamic_filters_json": "{}",
 "filters_json": "{\"company\":\"Uttamenergy Limited\",\"account\":[\"2301010100 - IOB CC AC 4 - UEL\"],\"group_by\":\"Group by Voucher (Consolidated)\",\"include_dimensions\":0,\"show_opening_entries\":0,\"include_default_book_entries\":0,\"show_cancelled_entries\":0,\"show_net_values_in_party_account\":1,\"to_date\":\"2021-12-01\",\"from_date\":\"2021-11-01\"}",
 "function": "Count",
 "idx": 0,
 "is_public": 1,
 "is_standard": 1,
 "label": "CC Limit",
 "modified": "2021-12-01 11:50:30.997516",
 "modified_by": "asoral@dexciss.com",
 "module": "Accounts",
 "name": "CC Limit",
 "owner": "asoral@dexciss.com",
 "report_field": "balance",
 "report_function": "Average",
 "report_name": "General Ledger",
 "show_percentage_stats": 1,
 "stats_time_interval": "Daily",
 "type": "Report"
}